{
  "comp": {
    "switch": {
      "bg": {
        "$type": "color",
        "$value": "{output.color.accent.primary}"
      },
      "fg": {
        "$type": "color",
        "$value": "{modify.interaction.color.fg.text}"
      },
      "stroke": {
        "$type": "color",
        "$value": "{output.color.accent.stroke}"
      },
      "b-rad": {
        "$type": "dimension",
        "$value": "{output.dimension.fixed-8}"
      },
      "gap": {
        "$type": "dimension",
        "$value": "{output.dimension.fixed-4}"
      },
      "pad": {
        "$type": "dimension",
        "$value": "{output.dimension.fixed-4}"
      },
      "stroke-w": {
        "$type": "dimension",
        "$value": "{modify.interaction.dimension.stroke}"
      }
    }
  }
}