{
  "input": {
    "0": {
      "$type": "number",
      "$value": "0"
    },
    "16": {
      "$type": "number",
      "$value": "16"
    },
    "24": {
      "$type": "number",
      "$value": "24"
    },
    "40": {
      "$type": "number",
      "$value": "40"
    }
  },
  "output": {
    "typography": {
      "large": {
        "$type": "typography",
        "$value": {
          "fontFamily": "Inter",
          "fontSize": "{input.40.$value}",
          "fontWeight": "Black"
        }
      },
      "medium": {
        "$type": "typography",
        "$value": {
          "fontFamily": "Inter",
          "fontSize": "{input.24.$value}",
          "fontWeight": "Semi Bold"
        }
      },
      "small": {
        "$type": "typography",
        "$value": {
          "fontFamily": "Inter",
          "fontSize": "{input.16.$value}",
          "fontWeight": "Regular"
        }
      }
    }
  },
  "colors": {
    "primary": {
      "$type": "color",
      "$value": "#1a56db"
    },
    "secondary": {
      "$type": "color",
      "$value": "#10b981"
    },
    "background": {
      "$type": "color",
      "$value": "#ffffff"
    },
    "text": {
      "primary": {
        "$type": "color",
        "$value": "#1f2937"
      },
      "secondary": {
        "$type": "color",
        "$value": "#6b7280"
      }
    }
  },
  "$themes": [],
  "$metadata": {
    "tokenSetOrder": ["input", "output", "colors"]
  }
}
