{
  "modify": {
    "interaction": {
      "string": {
        "name": {
          "$type": "string",
          "$value": "pressed"
        }
      },
      "state": {
        "stroke-width": {
          "$type": "dimension",
          "$value": "{input.dimension.1}"
        }
      },
      "color": {
        "surface": {
          "bg": {
            "$type": "color",
            "$value": "{modify.displaymode.color.bg.above.darker}"
          },
          "stroke": {
            "$type": "color",
            "$value": "{modify.displaymode.color.stroke.default}"
          }
        },
        "accent": {
          "color": {
            "$type": "color",
            "$value": "{modify.accent.color.pressed}"
          },
          "color-opacity": {
            "$type": "color",
            "$value": "{modify.accent.color.opacity-pressed}"
          },
          "focus": {
            "$type": "color",
            "$value": "null"
          }
        }
      },
      "shadow": {
        "numbers": {
          "1": {
            "x": {
              "$type": "number",
              "$value": "{input.number.shadow.small.1.x}"
            },
            "y": {
              "$type": "number",
              "$value": "{input.number.shadow.small.1.y}"
            },
            "blur": {
              "$type": "number",
              "$value": "{input.number.shadow.small.1.blur}"
            },
            "spread": {
              "$type": "number",
              "$value": "{input.number.shadow.small.1.spread}"
            }
          },
          "2": {
            "x": {
              "$type": "number",
              "$value": "{input.number.shadow.small.2.x}"
            },
            "y": {
              "$type": "number",
              "$value": "{input.number.shadow.small.2.y}"
            },
            "blur": {
              "$type": "number",
              "$value": "{input.number.shadow.small.2.blur}"
            },
            "spread": {
              "$type": "number",
              "$value": "{input.number.shadow.small.2.spread}"
            }
          },
          "3": {
            "x": {
              "$type": "number",
              "$value": "{input.number.shadow.small.3.x}"
            },
            "y": {
              "$type": "number",
              "$value": "{input.number.shadow.small.3.y}"
            },
            "blur": {
              "$type": "number",
              "$value": "{input.number.shadow.small.3.blur}"
            },
            "spread": {
              "$type": "number",
              "$value": "{input.number.shadow.small.3.spread}"
            }
          }
        }
      }
    }
  }
}